rota/__init__.py
rota/__main__.py
rota/cmds/__init__.py
rota/cmds/cmd_build.py
rota/cmds/cmd_config.py
rota/cmds/cmd_down.py
rota/cmds/cmd_play.py
rota/cmds/cmd_rep.py
rota/cmds/cmd_run.py
rota/down/__init__.py
rota/down/drafts.py
rota/game/__init__.py
rota/game/cluster.py
rota/game/game.py
rota/game/game_builder.py
rota/game/game_validator.py
rota/game/graph.py
rota/game/quest.py
rota/game/task.py
rota/game/task_parser.py
rota/game/tree_item.py
rota/game/xp.py
rota/play/__init__.py
rota/play/border.py
rota/play/colors.py
rota/play/flags.py
rota/play/floating.py
rota/play/floating_manager.py
rota/play/fmt.py
rota/play/frame.py
rota/play/functors.py
rota/play/grade_message.py
rota/play/gui.py
rota/play/images.py
rota/play/input_manager.py
rota/play/keys.py
rota/play/language_setter.py
rota/play/opener.py
rota/play/patch_history.py
rota/play/play.py
rota/play/play_actions.py
rota/play/play_palette.py
rota/play/search.py
rota/play/task_graph.py
rota/play/tasktree.py
rota/play/tester.py
rota/play/tracker.py
rota/play/week_graph.py
rota/run/__init__.py
rota/run/diff_builder.py
rota/run/diff_builder_down.py
rota/run/diff_builder_side.py
rota/run/loader.py
rota/run/solver_builder.py
rota/run/unit.py
rota/run/unit_runner.py
rota/run/wdir.py
rota/run/writer.py
rota/settings/__init__.py
rota/settings/app_settings.py
rota/settings/check_version.py
rota/settings/history_file.py
rota/settings/listener_daily.py
rota/settings/listener_task.py
rota/settings/listener_week.py
rota/settings/log_action.py
rota/settings/log_info.py
rota/settings/logger.py
rota/settings/repository.py
rota/settings/repository_starter.py
rota/settings/settings.py
rota/settings/task_basic.py
rota/util/__init__.py
rota/util/code_filter.py
rota/util/compare.py
rota/util/consts.py
rota/util/decoder.py
rota/util/freerun.py
rota/util/get_md_link.py
rota/util/guide.py
rota/util/identifier.py
rota/util/label_factory.py
rota/util/param.py
rota/util/pattern.py
rota/util/raw_terminal.py
rota/util/remote_md.py
rota-2.6.2.dist-info/METADATA
rota-2.6.2.dist-info/WHEEL
rota-2.6.2.dist-info/entry_points.txt
rota-2.6.2.dist-info/top_level.txt
rota-2.6.2.dist-info/RECORD
